mindsdb/__about__.py
mindsdb/__init__.py
mindsdb/scraps.py
mindsdb/config/__init__.py
mindsdb/config/helpers.py
mindsdb/external_libs/__init__.py
mindsdb/external_libs/stats.py
mindsdb/libs/__init__.py
mindsdb/libs/backends/__init__.py
mindsdb/libs/backends/lightwood.py
mindsdb/libs/backends/ludwig.py
mindsdb/libs/constants/__init__.py
mindsdb/libs/constants/mindsdb.py
mindsdb/libs/controllers/__init__.py
mindsdb/libs/controllers/predictor.py
mindsdb/libs/controllers/transaction.py
mindsdb/libs/data_sources/__init__.py
mindsdb/libs/data_sources/file_ds.py
mindsdb/libs/data_types/__init__.py
mindsdb/libs/data_types/data_source.py
mindsdb/libs/data_types/mindsdb_logger.py
mindsdb/libs/data_types/probability_evaluation.py
mindsdb/libs/data_types/transaction_data.py
mindsdb/libs/data_types/transaction_output_data.py
mindsdb/libs/data_types/transaction_output_row.py
mindsdb/libs/helpers/__init__.py
mindsdb/libs/helpers/explain_prediction.py
mindsdb/libs/helpers/file_helpers.py
mindsdb/libs/helpers/general_helpers.py
mindsdb/libs/helpers/multi_data_source.py
mindsdb/libs/helpers/parser.py
mindsdb/libs/helpers/probabilistic_validator.py
mindsdb/libs/helpers/sqlite_helpers.py
mindsdb/libs/helpers/text_helpers.py
mindsdb/libs/helpers/train_helpers.py
mindsdb/libs/phases/__init__.py
mindsdb/libs/phases/base_module.py
mindsdb/libs/phases/data_extractor/__init__.py
mindsdb/libs/phases/data_extractor/data_extractor.py
mindsdb/libs/phases/data_transformer/__init__.py
mindsdb/libs/phases/data_transformer/data_transformer.py
mindsdb/libs/phases/model_analyzer/__init__.py
mindsdb/libs/phases/model_analyzer/model_analyzer.py
mindsdb/libs/phases/model_analyzer/helpers/__init__.py
mindsdb/libs/phases/model_analyzer/helpers/column_evaluator.py
mindsdb/libs/phases/model_interface/__init__.py
mindsdb/libs/phases/model_interface/model_interface.py
mindsdb/libs/phases/stats_generator/__init__.py
mindsdb/libs/phases/stats_generator/scores.py
MindsDB-1.3.1.dist-info/LICENSE
MindsDB-1.3.1.dist-info/METADATA
MindsDB-1.3.1.dist-info/WHEEL
MindsDB-1.3.1.dist-info/top_level.txt
MindsDB-1.3.1.dist-info/RECORD
