Metadata-Version: 2.1
Name: MindsDB
Version: 1.3.1
Summary: MindsDB's goal is to make it very simple for developers to use the power of artificial neural networks in their projects.
Home-page: https://github.com/mindsdb/mindsdb
Author: MindsDB Inc
Author-email: jorge@mindsdb.com
License: MIT
Download-URL: https://pypi.org/project/mindsdb
Platform: UNKNOWN
Classifier: Programming Language :: Python :: 3
Classifier: License :: OSI Approved :: MIT License
Classifier: Operating System :: OS Independent
Requires-Python: >=3.6
Requires-Dist: scikit-image (==0.14.2)
Requires-Dist: cython (>=0.29.2)
Requires-Dist: setuptools (>=21.2.1)
Requires-Dist: wheel (>=0.32.2)
Requires-Dist: attrs (>=18.2.0)
Requires-Dist: numpy (>=1.15.2)
Requires-Dist: pandas (>=0.23.4)
Requires-Dist: python-dateutil (>=2.7.3)
Requires-Dist: pytz (>=2018.5)
Requires-Dist: requests (>=2.20.0)
Requires-Dist: scipy (>=1.1.0)
Requires-Dist: scikit-learn (>=0.20.3)
Requires-Dist: colorlog (>=4.0.2)
Requires-Dist: tensorflow (==1.13.1)
Requires-Dist: tensorflow-estimator (==1.13.0)
Requires-Dist: ludwig (==0.1.2)
Requires-Dist: xlrd (>=1.0.0)
Requires-Dist: ImageHash (==4.0)
Requires-Dist: imageio (==2.5.0)
Requires-Dist: lightwood (==0.7.3)
